<annotation>
	<folder>yolo_data</folder>
	<filename>22.png</filename>
	<path>/home/airo/robot_ws/src/camera_node/yolo_data/22.png</path>
	<source>
		<database>Unknown</database>
	</source>
	<size>
		<width>1920</width>
		<height>1080</height>
		<depth>3</depth>
	</size>
	<segmented>0</segmented>
	<object>
		<name>hole</name>
		<pose>Unspecified</pose>
		<truncated>0</truncated>
		<difficult>0</difficult>
		<bndbox>
			<xmin>1124</xmin>
			<ymin>354</ymin>
			<xmax>1189</xmax>
			<ymax>414</ymax>
		</bndbox>
	</object>
	<object>
		<name>hole</name>
		<pose>Unspecified</pose>
		<truncated>0</truncated>
		<difficult>0</difficult>
		<bndbox>
			<xmin>1216</xmin>
			<ymin>351</ymin>
			<xmax>1262</xmax>
			<ymax>391</ymax>
		</bndbox>
	</object>
	<object>
		<name>hole</name>
		<pose>Unspecified</pose>
		<truncated>0</truncated>
		<difficult>0</difficult>
		<bndbox>
			<xmin>1289</xmin>
			<ymin>327</ymin>
			<xmax>1353</xmax>
			<ymax>374</ymax>
		</bndbox>
	</object>
</annotation>
